setup_server.py
mess_server_fatfar.egg-info/PKG-INFO
mess_server_fatfar.egg-info/SOURCES.txt
mess_server_fatfar.egg-info/dependency_links.txt
mess_server_fatfar.egg-info/requires.txt
mess_server_fatfar.egg-info/top_level.txt
server/__init__.py
server/decos.py
server/descriptors.py
server/errors.py
server/metaclass.py
server/server.py
server/common/__init__.py
server/common/utils.py
server/common/variables.py
server/configs/__init__.py
server/configs/config_client_log.py
server/configs/config_server_log.py
server/doc/__init__.py
server/doc/source/__init__.py
server/doc/source/conf.py
server/server/__init__.py
server/server/add_user.py
server/server/config_window.py
server/server/core.py
server/server/main_window.py
server/server/remove_user.py
server/server/server_db.py
server/server/stat_window.py