Metadata-Version: 1.0
Name: mess-server-fatfar
Version: 0.0.1
Summary: mess_server
Home-page: UNKNOWN
Author: Farid Fatekhov
Author-email: fatfar@yandex.ru
License: UNKNOWN
Platform: UNKNOWN
